pyDAC/DAC.py
pyDAC/__init__.py
pyDAC-0.0.2.dist-info/METADATA
pyDAC-0.0.2.dist-info/WHEEL
pyDAC-0.0.2.dist-info/top_level.txt
pyDAC-0.0.2.dist-info/RECORD
